{"_type":"export","__export_format":4,"__export_date":"2022-01-05T21:01:59.251Z","__export_source":"insomnia.desktop.app:v2021.7.2","resources":[{"_id":"req_f8ffcd8d972e4e4794937787dfc83971","parentId":"fld_aa0118bae22d411ab7dfa4809a4e4d3c","modified":1641416342567,"created":1641395771821,"url":"{{ _.URL }}/task/filter/late/11-11-11-11-11-11","name":"Late","description":"","method":"GET","body":{},"parameters":[],"headers":[],"authentication":{},"metaSortKey":-1641395771821,"isPrivate":false,"settingStoreCookies":true,"settingSendCookies":true,"settingDisableRenderRequestBody":false,"settingEncodeUrl":true,"settingRebuildPath":true,"settingFollowRedirects":"global","_type":"request"},{"_id":"fld_aa0118bae22d411ab7dfa4809a4e4d3c","parentId":"wrk_cf2cf6d1c9ab46a980c988580d7c032f","modified":1641336396315,"created":1641336396315,"name":"TASK","description":"","environment":{},"environmentPropertyOrder":null,"metaSortKey":-1641336396315,"_type":"request_group"},{"_id":"wrk_cf2cf6d1c9ab46a980c988580d7c032f","parentId":null,"modified":1641336382624,"created":1641336382624,"name":"BACKEND","description":"","scope":"collection","_type":"workspace"},{"_id":"req_02f621b9ff1e443fb4e15ac032541a5a","parentId":"fld_aa0118bae22d411ab7dfa4809a4e4d3c","modified":1641416353972,"created":1641412896800,"url":"{{ _.URL }}/task/filter/today/11-11-11-11-11-11","name":"Today","description":"","method":"GET","body":{},"parameters":[],"headers":[],"authentication":{},"metaSortKey":-1641394448093,"isPrivate":false,"settingStoreCookies":true,"settingSendCookies":true,"settingDisableRenderRequestBody":false,"settingEncodeUrl":true,"settingRebuildPath":true,"settingFollowRedirects":"global","_type":"request"},{"_id":"req_d1b714e8c4d14407abe446ae3e2da635","parentId":"fld_aa0118bae22d411ab7dfa4809a4e4d3c","modified":1641416366808,"created":1641413271201,"url":"{{ _.URL }}/task/filter/week/11-11-11-11-11-11","name":"Week","description":"","method":"GET","body":{},"parameters":[],"headers":[],"authentication":{},"metaSortKey":-1641393786229,"isPrivate":false,"settingStoreCookies":true,"settingSendCookies":true,"settingDisableRenderRequestBody":false,"settingEncodeUrl":true,"settingRebuildPath":true,"settingFollowRedirects":"global","_type":"request"},{"_id":"req_17e176ad91874006b716c2ad10e21a0a","parentId":"fld_aa0118bae22d411ab7dfa4809a4e4d3c","modified":1641416460475,"created":1641413419207,"url":"{{ _.URL }}/task/filter/month/11-11-11-11-11-11","name":"Month","description":"","method":"GET","body":{},"parameters":[],"headers":[],"authentication":{},"metaSortKey":-1641393455297,"isPrivate":false,"settingStoreCookies":true,"settingSendCookies":true,"settingDisableRenderRequestBody":false,"settingEncodeUrl":true,"settingRebuildPath":true,"settingFollowRedirects":"global","_type":"request"},{"_id":"req_66e5e8e19df7491b9a1c3be95b184fbf","parentId":"fld_aa0118bae22d411ab7dfa4809a4e4d3c","modified":1641416480035,"created":1641414639366,"url":"{{ _.URL }}/task/filter/year/11-11-11-11-11-11","name":"Year","description":"","method":"GET","body":{},"parameters":[],"headers":[],"authentication":{},"metaSortKey":-1641393289831,"isPrivate":false,"settingStoreCookies":true,"settingSendCookies":true,"settingDisableRenderRequestBody":false,"settingEncodeUrl":true,"settingRebuildPath":true,"settingFollowRedirects":"global","_type":"request"},{"_id":"req_168420cc89684baba4d0ac09a593b61b","parentId":"fld_aa0118bae22d411ab7dfa4809a4e4d3c","modified":1641393899995,"created":1641393124322,"url":"{{ _.URL }}/task/61d5ad33b3abb908728909f3/false","name":"Done","description":"","method":"PUT","body":{},"parameters":[],"headers":[],"authentication":{},"metaSortKey":-1641393124365,"isPrivate":false,"settingStoreCookies":true,"settingSendCookies":true,"settingDisableRenderRequestBody":false,"settingEncodeUrl":true,"settingRebuildPath":true,"settingFollowRedirects":"global","_type":"request"},{"_id":"req_b04f0590491944bda43e7740fab39581","parentId":"fld_aa0118bae22d411ab7dfa4809a4e4d3c","modified":1641392541290,"created":1641392050222,"url":"{{ _.URL }}/task/61d4dab0945a735856ea5bb1","name":"Delete","description":"","method":"DELETE","body":{},"parameters":[],"headers":[],"authentication":{},"metaSortKey":-1641392050222,"isPrivate":false,"settingStoreCookies":true,"settingSendCookies":true,"settingDisableRenderRequestBody":false,"settingEncodeUrl":true,"settingRebuildPath":true,"settingFollowRedirects":"global","_type":"request"},{"_id":"req_9671d47851ea487296cb202ed688427e","parentId":"fld_aa0118bae22d411ab7dfa4809a4e4d3c","modified":1641413503946,"created":1641391935801,"url":"{{ _.URL }}/task/61d5f960d490d03b0415e7d5","name":"Show","description":"","method":"GET","body":{},"parameters":[],"headers":[],"authentication":{},"metaSortKey":-1641391935801,"isPrivate":false,"settingStoreCookies":true,"settingSendCookies":true,"settingDisableRenderRequestBody":false,"settingEncodeUrl":true,"settingRebuildPath":true,"settingFollowRedirects":"global","_type":"request"},{"_id":"req_0d971b3f67964cfdb092d2cbf0bd4552","parentId":"fld_aa0118bae22d411ab7dfa4809a4e4d3c","modified":1641415911446,"created":1641390705936,"url":"{{ _.URL }}/task/filter/all/11-11-11-11-11-11","name":"All","description":"","method":"GET","body":{},"parameters":[],"headers":[],"authentication":{},"metaSortKey":-1641390705936,"isPrivate":false,"settingStoreCookies":true,"settingSendCookies":true,"settingDisableRenderRequestBody":false,"settingEncodeUrl":true,"settingRebuildPath":true,"settingFollowRedirects":"global","_type":"request"},{"_id":"req_51e4fd250aad4e5c8094865c2bda8cb8","parentId":"fld_aa0118bae22d411ab7dfa4809a4e4d3c","modified":1641416429134,"created":1641340473013,"url":"{{ _.URL }}/task/61d5fab20f0b07af19eb20da","name":"Update","description":"","method":"PUT","body":{"mimeType":"application/json","text":"{\n  \"macaddress\": \"11-11-11-11-11-11\",\n  \"type\": 1, \n  \"title\": \"Comprar Café 2 atualizado de novo\",\n  \"description\": \"Em tal mercado está na promoção\",\n  \"when\": \"2022-01-07T16:40:00.000\"\n}"},"parameters":[],"headers":[{"name":"Content-Type","value":"application/json","id":"pair_1d4026267ef74b05a80c89a9bd66e63b"}],"authentication":{},"metaSortKey":-1641340473013,"isPrivate":false,"settingStoreCookies":true,"settingSendCookies":true,"settingDisableRenderRequestBody":false,"settingEncodeUrl":true,"settingRebuildPath":true,"settingFollowRedirects":"global","_type":"request"},{"_id":"req_07a3c2d41d7d445ebee1c6b984d57f14","parentId":"fld_aa0118bae22d411ab7dfa4809a4e4d3c","modified":1641415797940,"created":1641336524283,"url":"{{ _.URL }}/task","name":"Create","description":"","method":"POST","body":{"mimeType":"application/json","text":"{\n  \"macaddress\": \"11-11-11-11-11-11\",\n  \"type\": 1, \n  \"title\": \"Comprar hoje\",\n  \"description\": \"Em tal mercado está na promoção\",\n  \"when\": \"2022-01-07T19:30:00.000\"\n}"},"parameters":[],"headers":[{"name":"Content-Type","value":"application/json","id":"pair_7fa1bc6130554b36aa926cf5b7d3588a"}],"authentication":{},"metaSortKey":-1641336524283,"isPrivate":false,"settingStoreCookies":true,"settingSendCookies":true,"settingDisableRenderRequestBody":false,"settingEncodeUrl":true,"settingRebuildPath":true,"settingFollowRedirects":"global","_type":"request"},{"_id":"env_ce28de84d0312faf57aec54590862ef217d53f06","parentId":"wrk_cf2cf6d1c9ab46a980c988580d7c032f","modified":1641391243599,"created":1641336382632,"name":"Base Environment","data":{},"dataPropertyOrder":{},"color":null,"isPrivate":false,"metaSortKey":1641336382632,"_type":"environment"},{"_id":"jar_ce28de84d0312faf57aec54590862ef217d53f06","parentId":"wrk_cf2cf6d1c9ab46a980c988580d7c032f","modified":1641336382635,"created":1641336382635,"name":"Default Jar","cookies":[],"_type":"cookie_jar"},{"_id":"spc_2585b9a6d90c4cbeb2782263c094af5b","parentId":"wrk_cf2cf6d1c9ab46a980c988580d7c032f","modified":1641336382625,"created":1641336382625,"fileName":"BACKEND","contents":"","contentType":"yaml","_type":"api_spec"},{"_id":"env_7b1ed69c7e934dc1af99b34e620c83a9","parentId":"env_ce28de84d0312faf57aec54590862ef217d53f06","modified":1641391341078,"created":1641391250486,"name":"Desenvolvimento","data":{"URL":"http://localhost:3000"},"dataPropertyOrder":{"&":["URL"]},"color":"#2bca4b","isPrivate":false,"metaSortKey":1641391250486,"_type":"environment"}]}